kbench/__init__.py
kbench/__main__.py
kbench/consts.py
kbench/deployment.py
kbench/pod.py
kbench-0.5.0.dist-info/entry_points.txt
kbench-0.5.0.dist-info/LICENSE
kbench-0.5.0.dist-info/WHEEL
kbench-0.5.0.dist-info/METADATA
kbench-0.5.0.dist-info/RECORD
