Metadata-Version: 2.1
Name: kbench
Version: 0.5.0
Summary: Benchmarking tool for Kubernetes clusters
Home-page: https://github.com/keichi/kbench/
License: MIT
Author: Keichi Takahashi
Author-email: keichi.t@me.com
Requires-Python: >=3.7,<4.0
Classifier: Environment :: Console
Classifier: License :: OSI Approved :: MIT License
Classifier: Operating System :: OS Independent
Classifier: Programming Language :: Python :: 3
Classifier: Programming Language :: Python :: 3.7
Classifier: Programming Language :: Python :: 3.8
Classifier: Programming Language :: Python :: 3.9
Classifier: Topic :: System :: Benchmark
Classifier: Topic :: Utilities
Requires-Dist: click (>=8.0,<9.0)
Requires-Dist: kubernetes (>=18.20,<19.0)
Requires-Dist: loguru (>=0.5,<0.6)
Project-URL: Repository, https://github.com/keichi/kbench/
